{    
    "title": "Control Panel",
    "description": "",
    "version": "1.0",
    "image": {
        "src": "",
        "alt": ""
    },
    "include": {            
        "css": [
            "admin.css"
        ],
        "library": [
            "jquery",
            "jquery-ui",   
            "arikaim",
            "arikaim-ui",
            "semantic",
            "filepond",
            "tailwind"
        ],
        "loader": "system:loader"
    },
    "default-theme": "arikaim",
    "themes": {
        "default": {
            "title": "Default",
            "library": "semantic"
        },
        "arikaim": {
            "title": "Arikaim",
            "file": "semantic.min.css"
        }
    }
}